tk_alert/__init__.py
tk_alert/alert.py
tk_alert/alert_utils.py
tk_alert/constants.py
tk_alert/icons/error-icon.png
tk_alert/icons/information-icon.png
tk_alert/icons/success-icon.png
tk_alert/icons/warning-icon.png
tk_alert-0.0.2.dist-info/LICENSE.txt
tk_alert-0.0.2.dist-info/METADATA
tk_alert-0.0.2.dist-info/WHEEL
tk_alert-0.0.2.dist-info/notices.md
tk_alert-0.0.2.dist-info/top_level.txt
tk_alert-0.0.2.dist-info/RECORD
