Metadata-Version: 2.1
Name: tk-alert
Version: 0.0.2
Summary: Tkinter based package for sending GUI alerts / notifications.
Home-page: https://github.com/DragosPancescu/tk-alert
Author: Dragos Pancescu
Author-email: dragos.pnc@gmail.com
License: MIT
Platform: UNKNOWN
Classifier: License :: OSI Approved :: MIT License
Classifier: Programming Language :: Python :: 3.7
Classifier: Programming Language :: Python :: 3.8
Classifier: Programming Language :: Python :: 3.9
Classifier: Programming Language :: Python :: 3.10
Classifier: Programming Language :: Python :: 3.11
Classifier: Programming Language :: Python :: 3.12
Classifier: Operating System :: OS Independent
Requires-Python: >=3.7, <3.13
License-File: LICENSE.txt
License-File: notices.md
